setup.py
ssloop/__init__.py
ssloop/event.py
ssloop/loop.py
ssloop/net.py
ssloop.egg-info/PKG-INFO
ssloop.egg-info/SOURCES.txt
ssloop.egg-info/dependency_links.txt
ssloop.egg-info/top_level.txt
ssloop/impl/__init__.py
ssloop/impl/epoll_loop.py
ssloop/impl/kqueue_loop.py
ssloop/impl/select_loop.py