Metadata-Version: 1.0
Name: ssloop
Version: 0.0.4
Summary: super lightweight event loop
Home-page: http://github.com/clowwindy/ssloop
Author: clowwindy
Author-email: clowwindy42@gmail.com
License: MIT
Platform: UNKNOWN
